{
 "1329813126073286810": {
  "user": 899455359608033362,
  "sector": "Moderator",
  "timestamp": "1737126149",
  "question1": "f",
  "question2": "f",
  "question3": "f",
  "Role": 1320347265704923177,
  "Status": "Accepted"
 },
 "1329813123829596203": 899455359608033362,
 "1329813485948895252": {
  "user": 899455359608033362,
  "sector": "Exchanger",
  "timestamp": "1737126235",
  "question1": "r",
  "question2": "r",
  "question3": "r",
  "question4": "r",
  "question5": "r",
  "Role": 1320347094858338345,
  "Status": "Accepted"
 },
 "1329813482354507847": 899455359608033362,
 "1329813950992355359": {
  "user": 899455359608033362,
  "sector": "Moderator",
  "timestamp": "1737126346",
  "question1": "f",
  "question2": "f",
  "question3": "f",
  "Role": 1320347265704923177,
  "Status": "Accepted"
 },
 "1329813949641654313": 899455359608033362,
 "1329815341546864704": {
  "user": 899455359608033362,
  "sector": "Exchanger",
  "timestamp": "1737126677",
  "question1": "1",
  "question2": "1",
  "question3": "1",
  "question4": "1",
  "question5": "1",
  "Role": 1320347094858338345,
  "Status": "Accepted"
 },
 "1329815340053565451": 899455359608033362,
 "1329931647436456076": {
  "user": 330018581180055572,
  "sector": "Exchanger",
  "timestamp": "1737150813",
  "question1": "Test",
  "question2": "Test",
  "question3": "Test",
  "question4": "Test",
  "question5": "Test",
  "Role": 1320347094858338345,
  "Status": "Declined"
 },
 "1329931644928397322": 330018581180055572,
 "1330319285859385347": {
  "user": 767710591761907722,
  "sector": "Exchanger",
  "timestamp": "1737243233",
  "question1": "PayPal to Crypto",
  "question2": "I'm a bit experienced",
  "question3": "Idk",
  "question4": "Yes",
  "question5": "I'm ready to take on exchanges",
  "Role": 1320347094858338345,
  "Status": "Declined"
 },
 "1330319281241591809": 767710591761907722,
 "1330836479668125696": {
  "user": 980078415602417725,
  "sector": "Exchanger",
  "timestamp": "1737366542",
  "question1": "Test",
  "question2": "Test",
  "question3": "Test",
  "question4": "Test",
  "question5": "",
  "Role": 1320347094858338345,
  "Status": "Declined"
 },
 "1330836477524840489": 980078415602417725,
 "1330837028329361448": {
  "user": 1219279747343847586,
  "sector": "Moderator",
  "timestamp": "1737366673",
  "question1": "I already spoke with you about.",
  "question2": "Berlin (gmt +1)",
  "question3": "Already told",
  "Role": 1320347265704923177,
  "Status": "Declined"
 },
 "1330837026819543090": 1219279747343847586,
 "1330837204368490516": {
  "user": 939916402725359687,
  "sector": "Exchanger",
  "timestamp": "1737366715",
  "question1": "PayPal Exchanges and Crypto to Crypto",
  "question2": "2-3 months as a solo finding clients in marketplaces.",
  "question3": "\u20ac25",
  "question4": "Yes",
  "question5": "100+ Shiba Vouches and 200 vouches on my server :)",
  "Role": 1320347094858338345,
  "Status": "Declined"
 },
 "1330837202975981568": 939916402725359687,
 "1330837271590604883": {
  "user": 1316833524493582387,
  "sector": "Moderator",
  "timestamp": "1737366731",
  "question1": "ADMIN",
  "question2": "ADMIN",
  "question3": "FUCKING ADMIN",
  "Role": 1320347265704923177,
  "Status": "Declined"
 },
 "1330837269266829364": 1316833524493582387,
 "1330842919732514828": {
  "user": 341368870181011458,
  "sector": "Moderator",
  "timestamp": "1737368077",
  "question1": "I want to handle Tickets and help exchangers",
  "question2": "German",
  "question3": "I was ago few months Head admin in Gule Exchange server",
  "Role": 1320347265704923177,
  "Status": "Declined"
 },
 "1330842918633869362": 341368870181011458,
 "1330845978462388297": {
  "user": 735779124655685702,
  "sector": "Moderator",
  "timestamp": "1737368807",
  "question1": "Because i think i can help",
  "question2": "Berlin GMT 1 i think it is",
  "question3": "Yep ( its too many so i stop wont count them )",
  "Role": 1320347265704923177,
  "Status": "Declined"
 },
 "1330845976596054016": 735779124655685702,
 "1330877668652093490": {
  "user": 1305907744552779838,
  "sector": "Exchanger",
  "timestamp": "1737376362",
  "question1": ".",
  "question2": ".",
  "question3": ".",
  "question4": ".",
  "question5": ".",
  "Role": 1320347094858338345,
  "Status": "Accepted"
 },
 "1330877667087749153": 1305907744552779838,
 "1330948607377145856": {
  "user": 341368870181011458,
  "sector": "Exchanger",
  "timestamp": "1737393275",
  "question1": "bank,paysafe,amazon, revolut,zalando to eachother or ltc",
  "question2": "i had 2022 my last own exchange server but then i got more times termed so i didnt countine",
  "question3": "30\u20ac and for more deals i am ready to use mm",
  "question4": "yes",
  "question5": "my name is arda and i am 17 years old and i live in germany",
  "Role": 1320347094858338345,
  "Status": "Accepted"
 },
 "1330948606135373988": 341368870181011458,
 "1331005412404625408": {
  "user": 1324015262806052864,
  "sector": "Exchanger",
  "timestamp": "1737406819",
  "question1": "I2c c2i",
  "question2": "2 years",
  "question3": "10$",
  "question4": "Yes",
  "question5": "No",
  "Role": 1320347094858338345,
  "Status": "Declined"
 },
 "1331005410307608677": 1324015262806052864,
 "1331025079508664320": {
  "user": 1043250501573152829,
  "sector": "Exchanger",
  "timestamp": "1737411508",
  "question1": "Sex exchanges",
  "question2": "69 years",
  "question3": "69k\u20ac",
  "question4": "No my grandpaa will exchange for me",
  "question5": "",
  "Role": 1320347094858338345,
  "Status": "Declined"
 },
 "1331025077097201805": 1043250501573152829,
 "1331236091226886207": {
  "user": 767710591761907722,
  "sector": "Exchanger",
  "timestamp": "1737461817",
  "question1": "PayPal, Crypto and some more",
  "question2": "I'm experienced with exchanges",
  "question3": "Depends",
  "question4": "Yes",
  "question5": "",
  "Role": 1320347094858338345,
  "Status": "Accepted"
 },
 "1331236089658216473": 767710591761907722,
 "1331381953269600307": {
  "user": 1248658104942592061,
  "sector": "Exchanger",
  "timestamp": "1737496593",
  "question1": "p2c c2p c2c bank -> PayPal / Crypto",
  "question2": "1 year of experience in exchanging domain",
  "question3": "10$",
  "question4": "Yes, I do",
  "question5": "",
  "Role": 1320347094858338345,
  "Status": "Declined"
 },
 "1331381951386484776": 1248658104942592061,
 "1332648632977195008": {
  "user": 1219279747343847586,
  "sector": "Exchanger",
  "timestamp": "1737798593",
  "question1": "Pp2c\nC2pp",
  "question2": "\u2026",
  "question3": "40\u20ac",
  "question4": "Yes",
  "question5": "..",
  "Role": 1320347094858338345,
  "Status": "Accepted"
 },
 "1332648631173382195": 1219279747343847586,
 "1335183885608288306": {
  "user": 1225485827174432874,
  "sector": "Exchanger",
  "timestamp": "1738403044",
  "question1": "P2c c2c",
  "question2": "exchanger at easyexch, shopifa, used to be exchanger in old flareon",
  "question3": "15\u20ac",
  "question4": "Yes",
  "question5": "Nah",
  "Role": 1320347094858338345,
  "Status": "Declined"
 },
 "1335183884127703040": 1225485827174432874,
 "1335204803386675401": {
  "user": 1199410394888933447,
  "sector": "Exchanger",
  "timestamp": "1738408031",
  "question1": "LTC and Paypal",
  "question2": "Idk but I'm trusted",
  "question3": "Idk starting on low",
  "question4": "Yep",
  "question5": "Im trusted with 100+ vouches",
  "Role": 1320347094858338345,
  "Status": "Declined"
 },
 "1335204800576622623": 1199410394888933447,
 "1335209378415902750": {
  "user": 873961366023729224,
  "sector": "Exchanger",
  "timestamp": "1738409122",
  "question1": "Paypal Banktransfer C2C",
  "question2": "A lot trusted with over 7k in exchanges and sales",
  "question3": "5-25",
  "question4": "Yes all my crypto no messing around",
  "question5": "Online 14h a day and I can do exchanges all day longggg",
  "Role": 1320347094858338345,
  "Status": "Declined"
 },
 "1335209376016896073": 873961366023729224,
 "1335257351984386180": {
  "user": 1015690993770713220,
  "sector": "Exchanger",
  "timestamp": "1738420560",
  "question1": "From skrill to crypto",
  "question2": "Much Cause I send so much Solana to my bullx or phantom wallet",
  "question3": "What secruties?",
  "question4": "Yes",
  "question5": "Could you accept this Apply im going to try to show the best version of myself!",
  "Role": 1320347094858338345,
  "Status": "Declined"
 },
 "1335257350055137293": 1015690993770713220,
 "1335314103346004101": {
  "user": 1324508823053926403,
  "sector": "Exchanger",
  "timestamp": "1738434091",
  "question1": "apple pay to paypal, paypal to crypto, crypto to apple pay crypto paypal. and for crypto mainly ltc",
  "question2": "lots",
  "question3": "lots",
  "question4": "yes",
  "question5": "i have lots of experience and i am very trust worthy.",
  "Role": 1320347094858338345,
  "Status": "Declined"
 },
 "1335314101521354844": 1324508823053926403,
 "1335324282250596533": {
  "user": 1263894933421559850,
  "sector": "Exchanger",
  "timestamp": "1738436517",
  "question1": "yoo t3rm3d",
  "question2": "yoo t3rm3d",
  "question3": "yoo t3rm3d",
  "question4": "yoo t3rm3d",
  "question5": "yoo t3rm3d",
  "Role": 1320347094858338345,
  "Status": "Accepted"
 },
 "1335324281634033664": 1263894933421559850,
 "1335365886458073128": {
  "user": 1180153542745522217,
  "sector": "Exchanger",
  "timestamp": "1738446437",
  "question1": "p2c",
  "question2": "+6 months",
  "question3": "20\u20ac",
  "question4": "yes cb",
  "question5": ".",
  "Role": 1320347094858338345,
  "Status": "Declined"
 },
 "1335365884897792040": 1180153542745522217,
 "1335801931276222524": {
  "user": 746762070585901066,
  "sector": "Exchanger",
  "timestamp": "1738550398",
  "question1": "P2c, c2p , c2c",
  "question2": "good",
  "question3": "D\u00e9pend on tos",
  "question4": "Ye",
  "question5": "",
  "Role": 1320347094858338345,
  "Status": "Declined"
 },
 "1335801929628127375": 746762070585901066,
 "1336055738715475999": {
  "user": 270055348637794307,
  "sector": "Moderator",
  "timestamp": "1738610910",
  "question1": "To help",
  "question2": "EUROPE",
  "question3": "Yes",
  "Role": 1320347265704923177,
  "Status": "Declined"
 },
 "1336055737004331018": 270055348637794307,
 "1336090895472398357": {
  "user": 1082310137999532113,
  "sector": "Exchanger",
  "timestamp": "1738619292",
  "question1": "Paypal to ltc, Ltc to paypal, Usdt to paypal, Dogecoin to paypal",
  "question2": "Well I am an exchanger in one server and done a couple exchanges in DMs but not a lot",
  "question3": "Not sure",
  "question4": "Yes",
  "question5": "I am cute",
  "Role": 1320347094858338345,
  "Status": "Declined"
 },
 "1336090893387563010": 1082310137999532113,
 "1336092792673407178": {
  "user": 1082310137999532113,
  "sector": "Exchanger",
  "timestamp": "1738619744",
  "question1": "p2c, c2p",
  "question2": "a little bit",
  "question3": "not sure",
  "question4": "yes",
  "question5": "I am cute and I spoke to Traq in dms",
  "Role": 1320347094858338345,
  "Status": "Accepted"
 },
 "1336092790446362664": 1082310137999532113,
 "1336299123812470804": {
  "user": 1269953553208709151,
  "sector": "Exchanger",
  "timestamp": "1738668938",
  "question1": "P2c c2p",
  "question2": "Ja haut schon",
  "question3": "40\u20ac oder so",
  "question4": "Ja",
  "question5": "Ne au\u00dfer das wir uns kennen so von 63 checkste",
  "Role": 1320347094858338345,
  "Status": "Accepted"
 },
 "1336299121677434891": 1269953553208709151,
 "1336436364110991430": {
  "user": 270055348637794307,
  "sector": "Moderator",
  "timestamp": "1738701658",
  "question1": "Help",
  "question2": "Usa",
  "question3": "Bh",
  "Role": 1320347265704923177,
  "Status": "Declined"
 },
 "1336436362903027763": 270055348637794307,
 "1336633365729775690": {
  "user": 955331970861236263,
  "sector": "Exchanger",
  "timestamp": "1738748627",
  "question1": "P2c c2p c2c MM",
  "question2": "15k\u20ac+",
  "question3": "uh guys u know me do I have to",
  "question4": "kinda",
  "question5": "No thx",
  "Role": 1320347094858338345,
  "Status": "Accepted"
 },
 "1336633363032707083": 955331970861236263,
 "1336776368871968870": {
  "user": 1252289129945763893,
  "sector": "Exchanger",
  "timestamp": "1738782722",
  "question1": "p2c,c2c",
  "question2": "On maven shop",
  "question3": "10\u20ac",
  "question4": "Y i buyed coinbase",
  "question5": "",
  "Role": 1320347094858338345,
  "Status": "Accepted"
 },
 "1336776366951239773": 1252289129945763893,
 "1322238373984997471": {
  "message": 1336783623054950452,
  "sector": "Exchanger",
  "timestamp": "1738784451"
 },
 "1336783623054950452": {
  "user": 1322238373984997471,
  "sector": "Exchanger",
  "timestamp": "1738784451",
  "question1": "Bank to Crypto / PayPal to LTC\nCrypto / Crypto to PayPal",
  "question2": "I have 1 year Exchanger experience",
  "question3": "20-50\u20ac",
  "question4": "Yes I have coinbase",
  "question5": ":)",
  "Role": 1320347094858338345,
  "Status": "Pending"
 },
 "1336783621855379517": 1322238373984997471,
 "1337012620850626681": {
  "user": 316289705379627010,
  "sector": "Exchanger",
  "timestamp": "1738839049",
  "question1": "All",
  "question2": "A lot im exchanger in 6server rn",
  "question3": "400\u20ac",
  "question4": "Yes",
  "question5": "No",
  "Role": 1320347094858338345,
  "Status": "Declined"
 },
 "1337012619306864643": 316289705379627010,
 "1337175909123231826": {
  "user": 1279368665384484908,
  "sector": "Exchanger",
  "timestamp": "1738877980",
  "question1": "Pp2c",
  "question2": "2years",
  "question3": "No, am trusted",
  "question4": "Yes ,",
  "question5": "No",
  "Role": 1320347094858338345,
  "Status": "Declined"
 },
 "1337175907437252672": 1279368665384484908,
 "1337377703602421822": {
  "user": 1318291450764591180,
  "sector": "Moderator",
  "timestamp": "1738926091",
  "question1": "To help sv out",
  "question2": "GMT+5",
  "question3": "A lot, retired staff of so many servers",
  "Role": 1320347265704923177,
  "Status": "Declined"
 },
 "1337377701471846421": 1318291450764591180,
 "1337377852747681793": {
  "user": 1199410394888933447,
  "sector": "Moderator",
  "timestamp": "1738926127",
  "question1": "I want to help with this server",
  "question2": "Georgia GMT+4",
  "question3": "Yep i had 10+ 300+ members servers and been mod on like 5+ 1k members I've got 1 250 people rn",
  "Role": 1320347265704923177,
  "Status": "Declined"
 },
 "1337377849077927958": 1199410394888933447,
 "1337379112569802852": {
  "user": 1334627448964513793,
  "sector": "Moderator",
  "timestamp": "1738926427",
  "question1": "bcs i wanna help the server grow",
  "question2": "germany",
  "question3": "yep i was/am moderator in some other servers",
  "Role": 1320347265704923177,
  "Status": "Accepted"
 },
 "1337379110711726153": 1334627448964513793,
 "1337379466434838539": {
  "user": 316289705379627010,
  "sector": "Moderator",
  "timestamp": "1738926512",
  "question1": "I want to be a moderator to help this Server to grow and get big.\nI also like to help as much as I can and can bring new ideas, features to The server.\nI\u2019m very much Online so I can help fast and if someone needs me I\u2019m instant there.\nI want that everyone feel comfortable and follow the rules.",
  "question2": "Berlin (gmt+1)",
  "question3": "Yes a lot I\u2019m head admin in 3k member server, in a 2k shop server and also have much experience in few 800 member server.",
  "Role": 1320347265704923177,
  "Status": "Accepted"
 },
 "1337379465486925885": 316289705379627010,
 "1337381971206344785": {
  "user": 1247905761993162872,
  "sector": "Moderator",
  "timestamp": "1738927109",
  "question1": "I want to make the server a great place, grow the server, make it a fun, nice, safe place",
  "question2": "GMT+1",
  "question3": "yes, 4 years in \u224810 servers",
  "Role": 1320347265704923177,
  "Status": "Declined"
 },
 "1337381969864163398": 1247905761993162872,
 "1337390636545871905": {
  "user": 1219279747343847586,
  "sector": "Moderator",
  "timestamp": "1738929175",
  "question1": "I want to be moderator cause i want to help the Server to manage Tickets etc.\nIm very active und trustfull and can help to make this Server better.\nIm a very good moderator and help where i can.",
  "question2": "Berlin (gmt +1)",
  "question3": "Yes I\u2019m moderating in a 2,8k Member Server, in some little Server like 800 Member and in some more.",
  "Role": 1320347265704923177,
  "Status": "Declined"
 },
 "1337390634247524385": 1219279747343847586,
 "1337402162086547507": {
  "user": 760466385821499452,
  "sector": "Moderator",
  "timestamp": "1738931923",
  "question1": "No reason",
  "question2": "Gmt + 2",
  "question3": "Yes i owned 17-19 servers",
  "Role": 1320347265704923177,
  "Status": "Declined"
 },
 "1337402160794832956": 760466385821499452,
 "1337431545237082142": {
  "user": 1220588216177000491,
  "sector": "Moderator",
  "timestamp": "1738938928",
  "question1": "For checking tickets and help full for owner",
  "question2": "24 hours",
  "question3": "4 months experience",
  "Role": 1320347265704923177,
  "Status": "Declined"
 },
 "1337431542313779355": 1220588216177000491,
 "1337447579276939277": {
  "user": 1217090611564249092,
  "sector": "Exchanger",
  "timestamp": "1738942751",
  "question1": "Paypal crypto psc",
  "question2": "0",
  "question3": "10\u20ac",
  "question4": "No",
  "question5": "No",
  "Role": 1320347094858338345,
  "Status": "Declined"
 },
 "1337447576785522770": 1217090611564249092,
 "1337499042917388408": {
  "user": 1217090611564249092,
  "sector": "Moderator",
  "timestamp": "1738955021",
  "question1": "Yes, I am very active and can help",
  "question2": "Can Monday to Thursday 21:00 Friday to Sunday I don't have time",
  "question3": "No",
  "Role": 1320347265704923177,
  "Status": "Declined"
 },
 "1337499041663287307": 1217090611564249092,
 "1337540025885392967": {
  "user": 1261930403137323070,
  "sector": "Exchanger",
  "timestamp": "1738964792",
  "question1": "paypal to ltc",
  "question2": "to much",
  "question3": "20\u20ac",
  "question4": "yes",
  "question5": "iam a sigma",
  "Role": 1320347094858338345,
  "Status": "Accepted"
 },
 "1337540023716937839": 1261930403137323070,
 "1337577132229918730": {
  "user": 763831859405783101,
  "sector": "Exchanger",
  "timestamp": "1738973639",
  "question1": ".",
  "question2": ".",
  "question3": ".",
  "question4": ".",
  "question5": "I\n\nHave",
  "Role": 1320347094858338345,
  "Status": "Declined"
 },
 "1337577130774761553": 763831859405783101,
 "972953827856744558": {
  "message": 1338917503652597841,
  "sector": "Exchanger",
  "timestamp": "1739293208"
 },
 "1338917503652597841": {
  "user": 972953827856744558,
  "sector": "Exchanger",
  "timestamp": "1739293208",
  "question1": "pp/bank transfer = any crypto",
  "question2": "good amount",
  "question3": "dont know maybe like 10$ for now",
  "question4": "yes",
  "question5": "active alot , not lazy , cant work in school",
  "Role": 1320347094858338345,
  "Status": "Pending"
 },
 "1338917501496721408": 972953827856744558,
 "1338949653898465353": {
  "user": 270055348637794307,
  "sector": "Moderator",
  "timestamp": "1739300873",
  "question1": "So i cN help",
  "question2": "USA",
  "question3": "I do",
  "Role": 1320347265704923177,
  "Status": "Declined"
 },
 "1338949651998576764": 270055348637794307,
 "1339525930489483298": {
  "user": 1283004422389108787,
  "sector": "Moderator",
  "timestamp": "1739438268",
  "question1": "because it's an opportunity for me to make a significant impact",
  "question2": "UTC",
  "question3": "No",
  "Role": 1320347265704923177,
  "Status": "Declined"
 },
 "1339525929403158588": 1283004422389108787,
 "1272561433003167847": {
  "message": 1340014469568528464,
  "sector": "Exchanger",
  "timestamp": "1739554745"
 },
 "1340014469568528464": {
  "user": 1272561433003167847,
  "sector": "Exchanger",
  "timestamp": "1739554745",
  "question1": "Paypal to crypto, inr to crypto and vice versa",
  "question2": "I\u2019m in blockchain space for 4 years now, currently a memecoin trader and I do exchanges for my alpha group. So I know how it works, I just want to officially also become a crypto exchanger.",
  "question3": "Give me a price please I can put quite a sum",
  "question4": "Yes",
  "question5": "",
  "Role": 1320347094858338345,
  "Status": "Pending"
 },
 "1340014468289134592": 1272561433003167847,
 "1340391797804892211": {
  "user": 1279368665384484908,
  "sector": "Exchanger",
  "timestamp": "1739644707",
  "question1": "Paypal inr",
  "question2": "2years",
  "question3": "50",
  "question4": "Ye",
  "question5": "None",
  "Role": 1320347094858338345,
  "Status": "Declined"
 },
 "1340391796412518400": 1279368665384484908,
 "1340665901715947580": {
  "user": 1088803353993158737,
  "sector": "Exchanger",
  "timestamp": "1739710059",
  "question1": "Paypal,ltc,btc",
  "question2": "Afroo exchange currently exchanger",
  "question3": "50$",
  "question4": "yes",
  "question5": "no",
  "Role": 1320347094858338345,
  "Status": "Accepted"
 },
 "1340665899639636019": 1088803353993158737,
 "1340798423259152427": {
  "user": 341368870181011458,
  "sector": "Exchanger",
  "timestamp": "1739741654",
  "question1": "bank / paysafe / amazon to ltc",
  "question2": "2 year exchange owner \n1 year head staff of exchange server",
  "question3": "20\u20ac",
  "question4": "yes ofc",
  "question5": "",
  "Role": 1320347094858338345,
  "Status": "Accepted"
 },
 "1340798421107216534": 341368870181011458,
 "1341071560156647424": {
  "user": 1335639850069659679,
  "sector": "Exchanger",
  "timestamp": "1739806775",
  "question1": "BANK, paypal, crypto, paysafe, binance giftcard ETC...",
  "question2": "+30k exchanged",
  "question3": ":D",
  "question4": "yes",
  "question5": "I like farturas",
  "Role": 1320347094858338345,
  "Status": "Accepted"
 },
 "1341071558881574912": 1335639850069659679,
 "932663250200445030": {
  "message": 1341367134495707177,
  "sector": "Exchanger",
  "timestamp": "1739877246"
 },
 "1341367134495707177": {
  "user": 932663250200445030,
  "sector": "Exchanger",
  "timestamp": "1739877246",
  "question1": "I will able to do I2C and C2I exchanges",
  "question2": "I have well enough over 2month",
  "question3": "We can discuss that personally for better experience and understand",
  "question4": "Yes",
  "question5": "I am very fast and friendly",
  "Role": 1320347094858338345,
  "Status": "Pending"
 },
 "1341367132306407480": 932663250200445030,
 "1341377883511459841": {
  "user": 1308417247794040914,
  "sector": "Moderator",
  "timestamp": "1739879808",
  "question1": "because I want to gain more experience",
  "question2": "GMT +5:30",
  "question3": "yeah i have me own exchange server",
  "Role": 1320347265704923177,
  "Status": "Declined"
 },
 "1341377882055774271": 1308417247794040914,
 "1341503474667491430": {
  "user": 738124967740440680,
  "sector": "Exchanger",
  "timestamp": "1739909752",
  "question1": "P2C",
  "question2": "like 8 months",
  "question3": "idk the minimum but i\u2019ll normally do high exchanges with mm",
  "question4": "yeah",
  "question5": "",
  "Role": 1320347094858338345,
  "Status": "Accepted"
 },
 "1341503472176070768": 738124967740440680,
 "1341512179316297791": {
  "user": 1236262772652900435,
  "sector": "Exchanger",
  "timestamp": "1739911827",
  "question1": "PayPal\nCrypto\nRevoult\nPaysafecard\nBank\nGift cards",
  "question2": "Very much",
  "question3": "Yeah but i could also use an middleman for every deal",
  "question4": "Ye",
  "question5": "",
  "Role": 1320347094858338345,
  "Status": "Declined"
 },
 "1341512176858304563": 1236262772652900435,
 "1342027155428868200": {
  "user": 1243885308467220483,
  "sector": "Moderator",
  "timestamp": "1740034607",
  "question1": "Because i am active user of discord and i can manage this sercer",
  "question2": "5:30 gmt",
  "question3": "I have 3 year of experience in chilling servers",
  "Role": 1320347265704923177,
  "Status": "Declined"
 },
 "1342027154010931323": 1243885308467220483,
 "1342929122443137088": {
  "user": 1217090611564249092,
  "sector": "Exchanger",
  "timestamp": "1740249653",
  "question1": "Paypal crypto",
  "question2": "0",
  "question3": "10\u20ac",
  "question4": "No",
  "question5": "",
  "Role": 1320347094858338345,
  "Status": "Declined"
 },
 "1342929121201750186": 1217090611564249092,
 "1343221673842708542": {
  "user": 842389325597638676,
  "sector": "Moderator",
  "timestamp": "1740319402",
  "question1": "I want to help the server grow and maybe get a name for myself as well. I am really kind and Im active as hell so I would reply to the tickets really quickly and resolve any of their issues. I even have 140+ vouches on shiba.",
  "question2": "Ist",
  "question3": "Yes, have been a previous staff on fusion mm",
  "Role": 1320347265704923177,
  "Status": "Accepted"
 },
 "1343221671376457859": 842389325597638676,
 "1343223079924531272": {
  "user": 1217090611564249092,
  "sector": "Moderator",
  "timestamp": "1740319738",
  "question1": "I aktiv 24/7",
  "question2": "Montag bis Donnerstag 23:30 Freitag  bis Samstag 3:30",
  "question3": "No",
  "Role": 1320347265704923177,
  "Status": "Declined"
 },
 "1343223078364385360": 1217090611564249092,
 "778631053836812329": {
  "message": 1343225654975402057,
  "sector": "Moderator",
  "timestamp": "1740320351"
 },
 "1343225654975402057": {
  "user": 778631053836812329,
  "sector": "Moderator",
  "timestamp": "1740320351",
  "question1": "i want to help and i have fun moderating",
  "question2": "cet",
  "question3": "yes, admin in many servers also 3k+",
  "Role": 1320347265704923177,
  "Status": "Pending"
 },
 "1343225648487071765": 778631053836812329,
 "1343262218460069999": {
  "user": 1219279747343847586,
  "sector": "Moderator",
  "timestamp": "1740329069",
  "question1": "I want to be a moderator to help this Server to grow and get big.\nI also like to help as much as I can and can bring new ideas, features to The server.\nI\u2019m very much Online so I can help fast and if someone needs me I\u2019m instant there.\nI want that everyone feel comfortable and follow the rules.",
  "question2": "Berlin (gmt+1)",
  "question3": "Yes very much I am moderating a 16k member server and some 1-3k member server (administrator) and in some little 800-1K server.",
  "Role": 1320347265704923177,
  "Status": "Declined"
 },
 "1343262215842828288": 1219279747343847586,
 "952042937825525821": {
  "message": 1343270583261073478,
  "sector": "Exchanger",
  "timestamp": "1740331063"
 },
 "1343270583261073478": {
  "user": 952042937825525821,
  "sector": "Exchanger",
  "timestamp": "1740331063",
  "question1": "Crypto to Inr",
  "question2": "ive worked for my friends group but he unfortunately shut it down",
  "question3": "100 rupees pm",
  "question4": "yea",
  "question5": "idk, i hardly have exams",
  "Role": 1320347094858338345,
  "Status": "Pending"
 },
 "1343270581864370207": 952042937825525821,
 "1318291450764591180": {
  "message": 1343279895983427654,
  "sector": "Moderator",
  "timestamp": "1740333284"
 },
 "1343279895983427654": {
  "user": 1318291450764591180,
  "sector": "Moderator",
  "timestamp": "1740333284",
  "question1": "I\u2019m gud at moderating servers & highly experianced",
  "question2": "Usa",
  "question3": "Yes lots of",
  "Role": 1320347265704923177,
  "Status": "Pending"
 },
 "1343279887640952882": 1318291450764591180,
 "886343246089953312": {
  "message": 1343487613306409013,
  "sector": "Moderator",
  "timestamp": "1740382807"
 },
 "1343487613306409013": {
  "user": 886343246089953312,
  "sector": "Moderator",
  "timestamp": "1740382807",
  "question1": "Applying for admin",
  "question2": "Applying for admin",
  "question3": "Applying for admin",
  "Role": 1320347265704923177,
  "Status": "Pending"
 },
 "1343487611984937022": 886343246089953312,
 "1343487922543919175": {
  "user": 1296763667093651507,
  "sector": "Exchanger",
  "timestamp": "1740382881",
  "question1": "p2c, c2p and c2c",
  "question2": "3 months",
  "question3": "uh do u guys have deposit n withdraw anytime system",
  "question4": "Yes",
  "question5": "200+ shiba vouches with some good high amount vouches too",
  "Role": 1320347094858338345,
  "Status": "Declined"
 },
 "1343487921176576041": 1296763667093651507,
 "1343496264771309659": {
  "user": 1226820067270987827,
  "sector": "Exchanger",
  "timestamp": "1740384870",
  "question1": "10$",
  "question2": "Starting",
  "question3": "5$",
  "question4": "Yes",
  "question5": "No",
  "Role": 1320347094858338345,
  "Status": "Declined"
 },
 "1343496263462817803": 1226820067270987827,
 "1343536611350024193": {
  "user": 1307020392736755838,
  "sector": "Exchanger",
  "timestamp": "1740394489",
  "question1": "All",
  "question2": "4 years",
  "question3": "Idk",
  "question4": "Yes",
  "question5": "No",
  "Role": 1320347094858338345,
  "Status": "Declined"
 },
 "1343536609349472359": 1307020392736755838,
 "1146850109284421687": {
  "message": 1343875234020982794,
  "sector": "Moderator",
  "timestamp": "1740475223"
 },
 "1343875234020982794": {
  "user": 1146850109284421687,
  "sector": "Moderator",
  "timestamp": "1740475223",
  "question1": "Because i have good experience in moderating and in past i used to moderate a server with 10k members",
  "question2": "GMT/5:30",
  "question3": "Yes i do have experience",
  "Role": 1320347265704923177,
  "Status": "Pending"
 },
 "1343875232771084309": 1146850109284421687,
 "1307452351518478357": {
  "message": 1343900773427449937,
  "sector": "Exchanger",
  "timestamp": "1740481312"
 },
 "1343900773427449937": {
  "user": 1307452351518478357,
  "sector": "Exchanger",
  "timestamp": "1740481312",
  "question1": "Crypto 2 Crypto.",
  "question2": "Owned multiple servers with several of thousands of members.",
  "question3": "The minimum for now.",
  "question4": "Yes.",
  "question5": "",
  "Role": 1320347094858338345,
  "Status": "Pending"
 },
 "1343900771997192192": 1307452351518478357,
 "761845647540224010": {
  "message": 1344075106481340521,
  "sector": "Exchanger",
  "timestamp": "1740522877"
 },
 "1344075106481340521": {
  "user": 761845647540224010,
  "sector": "Exchanger",
  "timestamp": "1740522877",
  "question1": "Paypal to crypto",
  "question2": "Alot",
  "question3": "??",
  "question4": "Yes",
  "question5": "Not really, i exchange daily lol",
  "Role": 1320347094858338345,
  "Status": "Pending"
 },
 "1344075105403404338": 761845647540224010,
 "1344076933578621022": {
  "user": 244713993502064650,
  "sector": "Exchanger",
  "timestamp": "1740523312",
  "question1": "Paypal to Crypto, Crypto to Crypto, Crypto to Paypal",
  "question2": "Lots",
  "question3": "0",
  "question4": "Yes",
  "question5": "",
  "Role": 1320347094858338345,
  "Status": "Declined"
 },
 "1344076925269839944": 244713993502064650,
 "1344079403012980817": {
  "user": 1132670594069057647,
  "sector": "Exchanger",
  "timestamp": "1740523901",
  "question1": "P2C",
  "question2": "I have 2 years of experience and +10.000\u20ac exchanfed",
  "question3": "20",
  "question4": "yes",
  "question5": "",
  "Role": 1320347094858338345,
  "Status": "Accepted"
 },
 "1344079401037594635": 1132670594069057647,
 "1344687752578596915": {
  "user": 1199410394888933447,
  "sector": "Exchanger",
  "timestamp": "1740668943",
  "question1": "P2C Or C2P",
  "question2": "Average",
  "question3": "100\u20ac+",
  "question4": "Yes",
  "question5": "I'm trusted with 200+ vouchs Own 600+ Member Server Too",
  "Role": 1320347094858338345,
  "Status": "Accepted"
 },
 "1344687749927665786": 1199410394888933447,
 "1217090611564249092": {
  "message": 1344948913383145513,
  "sector": "Moderator",
  "timestamp": "1740731208"
 },
 "1344948913383145513": {
  "user": 1217090611564249092,
  "sector": "Moderator",
  "timestamp": "1740731208",
  "question1": "I can do the trick for support and everything. I'm also very active and I'm happy to help you",
  "question2": "Sunday to Thursday 11:30 p.m. Friday to Saturday 3:00 a.m. = 4:00 a.m",
  "question3": "Unfortunately I don't have any, I'm sorry",
  "Role": 1320347265704923177,
  "Status": "Pending"
 },
 "1344948910778486857": 1217090611564249092,
 "1052136143304531979": {
  "message": 1345010156928499826,
  "sector": "Exchanger",
  "timestamp": "1740745810"
 },
 "1345010156928499826": {
  "user": 1052136143304531979,
  "sector": "Exchanger",
  "timestamp": "1740745810",
  "question1": "inr to crypto crypto to inr  ( i prefer ltc )",
  "question2": "ngl not much  for 2 months i did exchangeing",
  "question3": "5$",
  "question4": "yeah",
  "question5": "",
  "Role": 1320347094858338345,
  "Status": "Pending"
 },
 "1345010150078943273": 1052136143304531979,
 "1345452385031557300": {
  "user": 979041077665333348,
  "sector": "Exchanger",
  "timestamp": "1740851245",
  "question1": "Paysafe - bank- Paypal",
  "question2": "I have much Experience, also got an own marketplace and Website for Accounts and follower and that Stuff",
  "question3": "50\u20ac",
  "question4": "Yes",
  "question5": "Im a Professional seller, which now wants to go in to the Exchange Business too",
  "Role": 1320347094858338345,
  "Status": "Accepted"
 },
 "1345452382791929988": 979041077665333348,
 "502909704608022542": {
  "message": 1345493048297000991,
  "sector": "Exchanger",
  "timestamp": "1740860940"
 },
 "1345493048297000991": {
  "user": 502909704608022542,
  "sector": "Exchanger",
  "timestamp": "1740860940",
  "question1": "p2c, c2c, bank iban and uk, uk giftcards, skrill, wise and many more",
  "question2": "250+ shiba vouches",
  "question3": "i was gonna ask if i can have bypass maybe",
  "question4": "yes",
  "question5": "",
  "Role": 1320347094858338345,
  "Status": "Pending"
 },
 "1345493046724137084": 502909704608022542,
 "1345717874513281047": {
  "user": 283466860178178060,
  "sector": "Exchanger",
  "timestamp": "1740914543",
  "question1": "C2C p2c c2p",
  "question2": "I am an Exchanger in Fusion MM it has 4k+ members",
  "question3": "18$",
  "question4": "yes",
  "question5": "I got 250+ reps in shiba",
  "Role": 1320347094858338345,
  "Status": "Accepted"
 },
 "1345717873066381353": 283466860178178060,
 "1345789592187437288": {
  "user": 1315076407692496958,
  "sector": "Moderator",
  "timestamp": "1740931642",
  "question1": "nz",
  "question2": "nz",
  "question3": "3",
  "Role": 1320347265704923177,
  "Status": "Declined"
 },
 "1345789590635544667": 1315076407692496958,
 "1345827621715316840": {
  "user": 1035636879221067837,
  "sector": "Exchanger",
  "timestamp": "1740940709",
  "question1": "f",
  "question2": "f",
  "question3": "f",
  "question4": "f",
  "question5": "",
  "Role": 1320347094858338345,
  "Status": "Accepted"
 },
 "1345827620566204508": 1035636879221067837,
 "1346208538602766346": {
  "user": 1330281035602071614,
  "sector": "Exchanger",
  "timestamp": "1741031526",
  "question1": "pp2ltc ltc2pp",
  "question2": "very much",
  "question3": "6\u20ac",
  "question4": "no",
  "question5": "im very active",
  "Role": 1320347094858338345,
  "Status": "Accepted"
 },
 "1346208535888920738": 1330281035602071614,
 "1347097680232579163": {
  "user": 1219279747343847586,
  "sector": "Exchanger",
  "timestamp": "1741243514",
  "question1": "Pp2c c2pp paysafe2c amazon2c",
  "question2": "Very much exchanged in 15+ server and got 100+ shiba",
  "question3": "50 at first",
  "question4": "Yes",
  "question5": "No",
  "Role": 1320347094858338345,
  "Status": "Declined"
 },
 "1347097677627916308": 1219279747343847586,
 "1347126717113827400": {
  "user": 326033832119894027,
  "sector": "Exchanger",
  "timestamp": "1741250437",
  "question1": "P2C C2P",
  "question2": "A lot I guess",
  "question3": "50\u20ac",
  "question4": "Yes",
  "question5": "No",
  "Role": 1320347094858338345,
  "Status": "Accepted"
 },
 "1347126715628912663": 326033832119894027,
 "1347623100308525066": {
  "user": 341368870181011458,
  "sector": "Moderator",
  "timestamp": "1741368784",
  "question1": "I\u2019d like to start as a moderator here since I was a successful exchanger and now want to see what it\u2019s like to be a mod. FlipX has also grown close to my heart.",
  "question2": "I live in Germany (GMT+1).",
  "question3": "I was a Head Admin on other exchange servers, but there, you could only be an Admin or an Exchanger.",
  "Role": 1320347265704923177,
  "Status": "Accepted"
 },
 "1347623098463031296": 341368870181011458,
 "1348332789740601354": {
  "user": 813826741155135498,
  "sector": "Moderator",
  "timestamp": "1741537987",
  "question1": "I want only do c2p exchanges",
  "question2": "GMT",
  "question3": "yh",
  "Role": 1320347265704923177,
  "Status": "Declined"
 },
 "1348332788213878995": 813826741155135498,
 "1349004108232659027": {
  "user": 1219279747343847586,
  "sector": "Moderator",
  "timestamp": "1741698042",
  "question1": "I want to be a moderator cause im very experienced and want to help this server to grow and to make that everyone dont has any problems, i also bring new ideas to the Server and help to improve.",
  "question2": "Gmt+1",
  "question3": "Yes a lot! I\u2019m moderator in a few big server, in one 16k, in some 1-3k and in some little 800-1K member server.",
  "Role": 1320347265704923177,
  "Status": "Declined"
 },
 "1349004105825124403": 1219279747343847586,
 "735779124655685702": {
  "message": 1349140272017051689,
  "sector": "Exchanger",
  "timestamp": "1741730506"
 },
 "1349140272017051689": {
  "user": 735779124655685702,
  "sector": "Exchanger",
  "timestamp": "1741730506",
  "question1": "Pp2ltc bank amazon crypto",
  "question2": "Very long, like sunnys bizeps",
  "question3": "Sunny abi gib admin \ud83d\udc49\ud83d\udc48",
  "question4": "Klar",
  "question5": "Ich bin albaner \ud83c\udde6\ud83c\uddf1\ud83c\udde6\ud83c\uddf1\ud83c\udde6\ud83c\uddf1\ud83e\udd85\ud83e\udd85\ud83e\udd85\ud83e\udd85",
  "Role": 1320347094858338345,
  "Status": "Pending"
 },
 "1349140269890535436": 735779124655685702,
 "580998211620044801": {
  "message": 1349686854395363329,
  "sector": "Exchanger",
  "timestamp": "1741860821"
 },
 "1349686854395363329": {
  "user": 580998211620044801,
  "sector": "Exchanger",
  "timestamp": "1741860821",
  "question1": "All except for revolut and Zalando / Im German",
  "question2": "quite much",
  "question3": "20.. but i have a question",
  "question4": "yes",
  "question5": "i have a question",
  "Role": 1320347094858338345,
  "Status": "Pending"
 },
 "1349686847743463527": 580998211620044801,
 "1263894933421559850": {
  "message": 1349865711882735678,
  "sector": "Exchanger",
  "timestamp": "1741903464"
 },
 "1349865711882735678": {
  "user": 1263894933421559850,
  "sector": "Exchanger",
  "timestamp": "1741903464",
  "question1": "P2c c2p c2c binance gc",
  "question2": "A lot",
  "question3": "\u2026",
  "question4": "Yeah",
  "question5": "Nope",
  "Role": 1320347094858338345,
  "Status": "Pending"
 },
 "1349865710398083163": 1263894933421559850,
 "1350037354835873812": {
  "user": 1151142646413271270,
  "sector": "Exchanger",
  "timestamp": "1741944387",
  "question1": "p2c ,c2p",
  "question2": "2 years",
  "question3": "30 at first",
  "question4": "yes",
  "question5": "started at discord like 3-4 years",
  "Role": 1320347094858338345,
  "Status": "Accepted"
 },
 "1350037353078587402": 1151142646413271270,
 "1314228806168612989": {
  "message": 1350062950496600114,
  "sector": "Exchanger",
  "timestamp": "1741950490"
 },
 "1350062950496600114": {
  "user": 1314228806168612989,
  "sector": "Exchanger",
  "timestamp": "1741950490",
  "question1": "Paypal -> Crypto.     Crypto -> Paypal Paypal -> IBAN bank transfare so All Kinds of Paypal Bank and crypto exchanges plus giftcard exchanges sometimes",
  "question2": "Much I have my own Exchange Server aswell",
  "question3": "I mean just looking arround helping out here and there so id say like 20 for now",
  "question4": "Yes",
  "question5": "Feel free to ask any questions",
  "Role": 1320347094858338345,
  "Status": "Pending"
 },
 "1350062947283636245": 1314228806168612989
}